{"usd":"USD","btc":"Bitcoin","611":"SixEleven","9coin":"9Coin","acn":"AvonCoin","acp":"AnarchistsPrime","adcn":"Asiadigicoin","aib":"AdvancedInternetBlock","amber":"AmberCoin","apc":"AlpaCoin","arc":"ArcticCoin","atx":"ArtexCoin","bac":"BitAlphaCoin","bash":"LuckChain","bay":"BitBay","bhc":"BighanCoin","bigc":"BigCoin","bios":"BiosCrypto","bit":"First Bitcoin","biz":"BizCoin","bost":"BoostCoin","brit":"BritCoin","btchc":"BitcoinHashcore","btlc":"BitLuckCoin","btx":"BitcoinTX","btcs":"BitcoinScrypt","btq":"Bitquark","burn":"President Sanders","burst":"Burst","calc":"CaliphCoin","cashh":"CashCoin","ccrb":"CryptoCarbon","cesc":"CryptoEscudo","champ":"Champcoin","csh":"Cashout","cj":"CryptoJacksCoin","crc":"CoreCoin","cre":"Credits","creak":"CreakCoin","crpc":"CereiPayCoin","crw":"CROWN","cto":"Crypto","dash":"Dash","dbic":"DubaiCoin","ddc":"DragonDigitalCoin","deus":"DeusCoin","dime":"DimeCoin","dlc":"DollarCoin","doge":"DogeCoin","dov":"DoveCoin","draco":"DT Token","drm8":"Dream8coin","drz":"Droidz","eb3c":"EuroBitCoin","ec":"Eclipse","edrc":"EDRcoin","egc":"EverGreenCoin","el":"ElCoin","ele":"Elementrem","ery":"Eryllium","etc":"Ethereum Classic","eth":"Ethereum","fch":"FastCash","fcp":"FitCoinPlus","first":"FirsttC","fit":"FitCoin","fjc":"FujiCoin","fun":"AlphabetCoinFund","futc":"FutCoin","g1tao":"G1TAO","gary":"President Johnson","gb":"GoldBlocks","gbc":"GlobalCoin","gbrc":"GlobalBusinessRevolution","gld":"GoldCoin","gltc":"GlobalTradeCoin","gmx":"Goldmaxcoin","grc":"Gridcoin","heat":"HEAT ledger","hcc":"HappyCreatorCoin","hill":"President Clinton","hmp":"HempCoin","htc":"HitCoin","ibc":"IBCoin","iop":"Fermat","isl":"IslaCoin","jio":"JIO Token","kc":"Kcoin","klc":"KiloCoin","krc":"KRCoin","lc":"LontaiCoin","ldcn":"Landcoin","lfc":"BigLifeCoin","lin":"LineCoin","log":"WoodCoin","ltc":"Litecoin","lts":"LiteStarCoin","leo":"LEOcoin","ltcr":"Litecred","mbl":"MobileCash","mco":"Macro","mgm":"Magnum","mi":"Xiaomicoin","miu":"MIYUCoin","moin":"Moin","mtaic":"MountTaiCoin","nav":"NavCoin","newb":"Newbium","note":"DNotes","ntc":"NeptuneCoin","ntcc":"NeptuneClassic","nvc":"NovaCoin","nxt":"NXT","od":"OpenDollar","omni":"Omni","otx":"OTCCoin","prime":"PrimeChain","pbc":"PabyosiCoin","pcs":"PabyosiCoin Special","pec":"PeaceCoin","pizza":"PiZZAcoin","pres":"President Trump","psb":"Pesobit","rbies":"Rubies","rev":"Revenu","rhfc":"RHFCoin","royal":"RoyalCoin","rycn":"RoyalCoin 2.0","smly":"SmileyCoin","tesla":"TeslaCoilCoin","s8c":"S88Coin","sib":"SibCoin","song":"SongCoin","ssc":"SunShotCoin","sts":"STRESScoin","tao":"TaoPay","tcash":"TaoCash","tcoin":"T-coin","tera":"TeraCoin","terra":"Terra","trc":"TerraCoin","trump":"TrumpCoin","tsc":"TopStarCoin","u":"UCoin","ub":"UniversalBookingCoin","unc":"UNCoin","unct":"Uncredit","uno":"Unobtanium","usdt":"Tether","uta":"UtaCoin","vec2":"VectorCoin 2.0","vidz":"PureVidz","vltc":"VaultCoin","vrs":"VEROS","vta":"VirtaCoin","vtl":"VitalAir","wa":"WA Space","wcn":"Wcoin","wex":"WexCoin","wgc":"WorldGoldCoin","wop":"WorldPay","wrp":"Wrapper","x2c":"Xecoin","xaur":"Xaurum","xby":"Bitmox","xen":"Xenix","xfc":"ForeverCoin","xhi":"HiCoin","xid":"International Diamond","xltc":"LiteChain","xnc":"XNCCoin","xodus":"ExodusCoin","xspec":"SpectreCoin","xstc":"SafeTradeCoin","xto":"Tao","xtp":"Isotope","xvg":"Verge","yoc":"YoCoin","zbc":"Zblock","zcl":"Zclassic","zcoin":"ZeroCoin","zny":"BitZeny","zxt":"Zcrypt","sfe":"SafeCoin","stpc":"Stepcoin"}